pynavernews/__init__.py
pynavernews/extractor.py
pynavernews/main.py
pynavernews-0.1.0.dist-info/LICENSE
pynavernews-0.1.0.dist-info/METADATA
pynavernews-0.1.0.dist-info/WHEEL
pynavernews-0.1.0.dist-info/RECORD
