Metadata-Version: 2.1
Name: pynavernews
Version: 0.1.0
Summary: Naver News Scraper
License: Apache-2.0
Keywords: naver,news,dataset,nlp
Author: ilotoki0804
Author-email: ilotoki0804@gmail.com
Requires-Python: >=3.11,<4.0
Classifier: License :: OSI Approved :: Apache Software License
Classifier: Operating System :: OS Independent
Classifier: Programming Language :: Python :: 3
Classifier: Programming Language :: Python :: 3.11
Classifier: Programming Language :: Python :: 3.12
Classifier: Topic :: Scientific/Engineering :: Artificial Intelligence
Requires-Dist: beautifulsoup4 (>=4.12.3,<5.0.0)
Requires-Dist: canrevan (>=4.0.0,<5.0.0)
Requires-Dist: hxsoup (==0.4.1)
Requires-Dist: tqdm (>=4.66.1,<5.0.0)
